README.rst
setup.cfg
setup.py
ipynose/__init__.py
ipynose/ipynose.py
ipynose.egg-info/PKG-INFO
ipynose.egg-info/SOURCES.txt
ipynose.egg-info/dependency_links.txt
ipynose.egg-info/requires.txt
ipynose.egg-info/top_level.txt