Metadata-Version: 1.1
Name: ipynose
Version: 0.0.2
Summary: print nosetests result in the iPython notebook
Home-page: https://github.com/wikibootup/ipynose
Author: wikibootup
Author-email: wikibootup@gmail.com
License: MIT
Keywords: nose
Platform: UNKNOWN
Classifier: Development Status :: 3 - Alpha
Classifier: Intended Audience :: Developers
Classifier: Topic :: Software Development :: Libraries :: Python Modules
Classifier: License :: OSI Approved :: MIT License
Classifier: Programming Language :: Python :: 2.7
Classifier: Programming Language :: Python :: 3
